kkanchan/__init__.py
kkanchan-0.0.1.dist-info/License.txt
kkanchan-0.0.1.dist-info/METADATA
kkanchan-0.0.1.dist-info/WHEEL
kkanchan-0.0.1.dist-info/top_level.txt
kkanchan-0.0.1.dist-info/RECORD
