Metadata-Version: 2.1
Name: kkanchan
Version: 0.0.1
Summary: The is a sample package
Author: Kanchan Bora
Classifier: Programming Language :: Python :: 3
Classifier: License :: OSI Approved :: MIT License
Classifier: Operating System :: OS Independent
Requires-Python: >=3.6
License-File: License.txt
